{
  "posts": [
    {
      "title": "신년5",
      "content": "추카추카~",
      "createdAt": "2025-01-01",
      "id": 1
    },
    {
      "title": "테스트",
      "content": "테스트 서버입니다\n",
      "createdAt": "2025-01-03",
      "id": 9
    },
    {
      "title": "최신",
      "content": "글입니다?\n\n",
      "createdAt": "2025-11-03",
      "id": 10
    },
    {
      "title": "가상",
      "content": "가상글",
      "createdAt": "2024-08-03",
      "id": 11
    },
    {
      "title": "터미",
      "content": "네이터",
      "createdAt": "2024-05-03",
      "id": 12
    },
    {
      "title": "오래된",
      "content": "글입니다",
      "createdAt": "2024-01-03",
      "id": 14
    },
    {
      "title": "24년",
      "content": "겨울이였다",
      "createdAt": "2024-03-03",
      "id": 15
    },
    {
      "title": "1",
      "content": "1",
      "createdAt": "2025-01-09",
      "id": 16
    },
    {
      "title": "2",
      "content": "2",
      "createdAt": "2025-01-09",
      "id": 17
    },
    {
      "title": "3",
      "content": "3",
      "createdAt": "2025-01-09",
      "id": 18
    },
    {
      "title": "4",
      "content": "44",
      "createdAt": "2025-01-09",
      "id": 19
    },
    {
      "title": "5",
      "content": "55",
      "createdAt": "2025-01-09",
      "id": 20
    },
    {
      "title": "6",
      "content": "66",
      "createdAt": "2025-01-09",
      "id": 21
    },
    {
      "title": "7",
      "content": "77",
      "createdAt": "2025-01-09",
      "id": 22
    },
    {
      "title": "8",
      "content": "88",
      "createdAt": "2025-01-09",
      "id": 23
    },
    {
      "title": "9",
      "content": "99",
      "createdAt": "2025-01-09",
      "id": 24
    },
    {
      "title": "10",
      "content": "1010",
      "createdAt": "2025-01-09",
      "id": 25
    },
    {
      "title": "매우긴이름 테스트매우긴이름 테스트매우긴이름 테스트매우긴이름 테스트",
      "content": "매우긴이름 테스트매우긴이름 테스트매우긴이름 테스트매우긴이름 테스트매우긴이름 테스트매우긴이름 테스트매우긴이름 테스트매우긴이름 테스트",
      "createdAt": "2025-01-09",
      "id": 26
    }
  ]
}